{
  "$schema": "https://mintlify.com/docs.json",
  "name": "Inspatial Cloud Client",
  "theme": "palm",
  "colors": {
    "primary": "#2563EB",
    "light": "#60A5FA",
    "dark": "#1E40AF"
  },
  "navbar": {
    "primary": {
      "type": "github",
      "href": "https://github.com/inspatiallabs/cloud-client"
    }
  },
  "footer": {
    "socials": {
      "github": "https://github.com/inspatiallabs/cloud-client"
    }
  },
  "navigation": {
    "tabs": [
      {
        "tab": "Documentation",
        "groups": [
          {
            "group": "Get Started",
            "pages": [
              "introduction",
              "installation",
              "quickstart"
            ]
          },
          {
            "group": "Core Concepts",
            "pages": [
              "concepts/cloud-client",
              "concepts/live-client",
              "concepts/entries",
              "concepts/settings"
            ]
          },
          {
            "group": "Guides",
            "pages": [
              "guides/authentication",
              "guides/entries-crud",
              "guides/real-time-events",
              "guides/file-uploads",
              "guides/filtering-queries"
            ]
          }
        ]
      },
      {
        "tab": "API Reference",
        "groups": [
          {
            "group": "Cloud API",
            "pages": [
              "api/cloud-client",
              "api/auth-group",
              "api/entry-group",
              "api/settings-group",
              "api/orm-group"
            ]
          },
          {
            "group": "Live Client",
            "pages": [
              "api/live-client",
              "api/live-events"
            ]
          },
          {
            "group": "Types",
            "pages": [
              "api/types/entry-types",
              "api/types/field-types",
              "api/types/settings-types",
              "api/types/filter-types"
            ]
          },
          {
            "group": "Utilities",
            "pages": [
              "api/mime-types",
              "api/currencies"
            ]
          }
        ]
      }
    ]
  }
}
